Workbook

Sheet README
A1: OPS Management System — Phase 1 Budget Model
A2: Client budget: 300,000 EGP · Window: 10 Aug – 20 Nov 2026 · Team: BE + FE + DevOps
A4: Purpose | B4: Models the Phase 1 build against a fixed 300,000 EGP client budget, and states explicitly what that budget does and does not buy.
A5: How to use it | B5: Edit only the blue cells on the Assumptions sheet. Every other figure in the workbook is a formula and will recalculate.
A6: Colour legend | B6: BLUE text = input you can change · BLACK = calculated · GREEN = pulled from another sheet · YELLOW fill = assumption the client must confirm.
A7: Balancing figure | B7: Contingency is calculated as budget − labour − infrastructure. The grand total therefore always equals the budget exactly.
A9: Headline | B9: The budget funds ~8.3 person-months. That covers the Phase 1 scope in the technical proposal and nothing beyond it.
A10: Key constraint | B10: Bringing returns in-house costs ~3 person-weeks more than the E-stebdal integration it replaces. This was absorbed by moving the customer self-service portal to Phase 1b — which leaves Phase 1 with NO slack.
A11: Implication | B11: Any scope added after Sprint 0 must displace something else. See the Sensitivity sheet for the three levers available.
A12: Scope change | B12: Authentication and the Super Admin console were added after the first draft. They cost ~10 days inside Phase 1, paid for by moving three read-only surfaces to Phase 1b. See the Scope Changes sheet.
A14: Sheets | B14: Assumptions · Resource Allocation · Cost Breakdown · Infra and Tooling · Cash Flow · Scope Changes · Phase 1b and 2 · Sensitivity · ROI
A15: Source | B15: Figures derive from POC - Youssey Excelsheet.xlsx via scripts/extract_data.py and from published provider pricing (Aug 2026). Salary bands: Egyptian mid-level market, 18,000–42,000 EGP/month.

Sheet Assumptions
A1: Assumptions
A2: Edit the BLUE cells only. Yellow fill = confirm with the client.
A4: Assumption | B4: Value | C4: Unit | D4: Basis / source
A5: Client budget (Phase 1) | B5: 300000 | C5: EGP | D5: Client-stated budget
A6: Project start | B6: 2026-08-10 | C6: date | D6: Sprint 0 begins
A7: Code freeze / go-live | B7: 2026-11-20 | C7: date | D7: 7 days before Black Friday (27 Nov 2026)
A8: Black Friday | B8: 2026-11-27 | C8: date | D8: Fixed external date
A9: Project duration | B9: 15 | C9: weeks | D9: 10 Aug – 20 Nov 2026
A10: Weeks per month | B10: 4.345 | C10: weeks | D10: 52 / 12
A12: USD / EGP | B12: 50.25 | C12: EGP | D12: Market rate, Aug 2026
A13: EUR / EGP | B13: 55 | C13: EGP | D13: Derived from USD/EGP at EURUSD ~1.09
A15: Backend engineer — monthly cost | B15: 34000 | C15: EGP | D15: Mid-level Egyptian market; the critical role
A16: Frontend engineer — monthly cost | B16: 27000 | C16: EGP | D16: Mid-level; Livewire/Blade profile, not React-only
A17: DevOps engineer — monthly cost | B17: 35000 | C17: EGP | D17: Mid-level; part-time allocation
A19: Backend allocation | B19: 1 | C19: FTE | D19: Full time across all sprints
A20: Frontend allocation | B20: 1 | C20: FTE | D20: Full time across all sprints
A21: DevOps allocation | B21: 0.4 | C21: FTE | D21: Front-loaded Sprint 1, then part time
A23: Infrastructure months funded | B23: 5 | C23: months | D23: Aug–Dec 2026, covering hypercare
A25: Duration in months | B25: =B9/B10 | C25: months | D25: Project duration ÷ weeks per month
A26: Total person-months | B26: =(B19+B20+B21)*B25 | C26: person-mo | D26: Sum of FTE allocations × duration in months
A28: NOTE | B28: Team model is IN-HOUSE SALARIED. Contractor rates typically run 1.3–1.8× and agency rates 2–3× these figures — at either, 300,000 EGP would not fund the Phase 1 scope. See the Sensitivity sheet.

Sheet Resource Allocation
A1: Resource Allocation by Sprint
A2: FTE per role per sprint. Sprint effort is indicative; cost is driven by the Assumptions sheet.
A4: Sprint | B4: Dates | C4: Primary focus | D4: BE FTE | E4: FE FTE | F4: Ops FTE | G4: Person-weeks
A5: 0 | B5: 10–14 Aug | C5: Discovery, credentials, schema, CS return-policy workshop | D5: 1 | E5: 0.5 | F5: 1 | G5: =(D5+E5+F5)*1
A6: 1 | B6: 17–28 Aug | C6: Schema, RBAC, audit log, webhook inbox, Filament shell | D6: 1 | E6: 1 | F6: 0.8 | G6: =(D6+E6+F6)*2
A7: 2 | B7: 31 Aug–11 Sep | C7: Shopify adapter, order ingestion, item-level splitting | D7: 1 | E7: 1 | F7: 0.3 | G7: =(D7+E7+F7)*2
A8: 3 | B8: 14–25 Sep | C8: Bosta adapter, per-item AWB, status webhooks, flex-ship | D8: 1 | E8: 1 | F8: 0.3 | G8: =(D8+E8+F8)*2
A9: 4 | B9: 28 Sep–9 Oct | C9: Financial engine: snapshots, ledger, 3 business models | D9: 1 | E9: 1 | F9: 0.3 | G9: =(D9+E9+F9)*2
A10: 5 | B10: 12–23 Oct | C10: Returns & exchanges in-house, eligibility, reverse pickup | D10: 1 | E10: 1 | F10: 0.4 | G10: =(D10+E10+F10)*2
A11: 6 | B11: 26 Oct–6 Nov | C11: Settlement, reconciliation, vendor portal, migration | D11: 1 | E11: 1 | F11: 0.3 | G11: =(D11+E11+F11)*2
A12: UAT | B12: 9–20 Nov | C12: UAT, parallel run, load test, cutover, hypercare prep | D12: 1 | E12: 1 | F12: 0.6 | G12: =(D12+E12+F12)*2
C13: Total person-weeks | G13: =SUM(G5:G12)
A15: Why DevOps is 0.4 FTE | B15: Effort is front-loaded into Sprint 1 (environments, CI/CD, secrets, backups) and Sprint 5 (load test), with light steady-state work between. On a two-node deployment there is no Kubernetes or managed-broker work to justify a full-time role, and the hours are better spent on integrations — which is where the delivery risk actually sits.

Sheet Cost Breakdown
A1: Cost Breakdown — Phase 1
A2: Contingency is the balancing figure, so the grand total always equals the client budget exactly.
A4: Line item | B4: Monthly (EGP) | C4: FTE | D4: Months | E4: Total (EGP) | F4: % of budget | G4: Notes
A5: LABOUR
A6: Backend engineer | B6: =Assumptions!$B$15 | C6: =Assumptions!$B$19 | D6: =Assumptions!$B$25 | E6: =B6*C6*D6 | F6: =E6/Assumptions!$B$5 | G6: Owns integrations, item splitting, financial engine, returns module
A7: Frontend engineer | B7: =Assumptions!$B$16 | C7: =Assumptions!$B$20 | D7: =Assumptions!$B$25 | E7: =B7*C7*D7 | F7: =E7/Assumptions!$B$5 | G7: Filament theming, dashboards, vendor portal, print layouts, Phase 1b portal
A8: DevOps engineer | B8: =Assumptions!$B$17 | C8: =Assumptions!$B$21 | D8: =Assumptions!$B$25 | E8: =B8*C8*D8 | F8: =E8/Assumptions!$B$5 | G8: Environments, CI/CD, monitoring, backups, load test, cutover
A9: Labour subtotal | E9: =SUM(E6:E8) | F9: =E9/Assumptions!$B$5
A11: NON-LABOUR
A12: Infrastructure and tooling | B12: ='Infra and Tooling'!$E$18 | D12: =Assumptions!$B$23 | E12: ='Infra and Tooling'!$F$18 | F12: =E12/Assumptions!$B$5 | G12: Hosting, storage, CI, email, domain — itemised on the Infra sheet
A13: Contingency | E13: =Assumptions!$B$5-E9-E12 | F13: =E13/Assumptions!$B$5 | G13: BALANCING FIGURE = budget − labour − infrastructure. Covers integration surprises and the PDPL hosting fallback (see Sensitivity).
A15: GRAND TOTAL | E15: =E9+E12+E13 | F15: =E15/Assumptions!$B$5
A17: Check — total equals budget | B17: =IF(ROUND(E15-Assumptions!$B$5,2)=0,"OK — balances exactly","MISMATCH")
A19: Cost per person-month | B19: =E9/Assumptions!$B$26 | D19: Against the Egyptian mid-level band of 18,000–42,000 EGP/month, this sits mid-range — achievable, but not a rate that buys senior engineers.

Sheet Infra and Tooling
A1: Infrastructure and Tooling
A2: Recommended: Hetzner Cloud CX line (EU) fronted by Cloudflare. See proposal §8.
A4: Item | B4: Spec | C4: Native cost | D4: Currency | E4: EGP / month | F4: Total (EGP) | G4: Notes
A5: Application node | B5: CX43 — 8 vCPU / 16 GB | C5: 15.99 | D5: EUR | E5: =C5*Assumptions!$B$13 | F5: =E5*Assumptions!$B$23 | G5: Ops console, vendor portal, workers, scheduler
A6: Data node | B6: CX33 — 4 vCPU / 8 GB | C6: 8.49 | D6: EUR | E6: =C6*Assumptions!$B$13 | F6: =E6*Assumptions!$B$23 | G6: PostgreSQL 16 + Redis 7
A7: Staging | B7: CX23 — 2 vCPU / 4 GB | C7: 5.49 | D7: EUR | E7: =C7*Assumptions!$B$13 | F7: =E7*Assumptions!$B$23 | G7: Full stack, sandbox integration credentials
A8: Automated backups | B8: 20% of server cost | C8: 5.99 | D8: EUR | E8: =C8*Assumptions!$B$13 | F8: =E8*Assumptions!$B$23 | G8: Nightly snapshots, 30-day retention
A9: Object storage | B9: Storage Box 1 TB | C9: 5 | D9: EUR | E9: =C9*Assumptions!$B$13 | F9: =E9*Assumptions!$B$23 | G9: AWB PDFs, payout proofs, off-site backups
A10: Source control / CI | B10: GitHub Team, 3 seats | C10: 12 | D10: USD | E10: =C10*Assumptions!$B$12 | F10: =E10*Assumptions!$B$23 | G10: Actions free tier is sufficient
A11: Transactional email | B11: Amazon SES | C11: 5 | D11: USD | E11: =C11*Assumptions!$B$12 | F11: =E11*Assumptions!$B$23 | G11: AWB labels and payout notifications to vendors
A12: DNS / TLS / WAF / CDN | B12: Cloudflare free tier | C12: 0 | D12: USD | E12: =C12*Assumptions!$B$12 | F12: =E12*Assumptions!$B$23 | G12: Also provides DDoS protection
A13: Error tracking | B13: Sentry free tier | C13: 0 | D13: USD | E13: =C13*Assumptions!$B$12 | F13: =E13*Assumptions!$B$23 | G13: 5k events/month covers this volume
A14: Uptime monitoring | B14: Uptime Kuma (self-hosted) | C14: 0 | D14: USD | E14: =C14*Assumptions!$B$12 | F14: =E14*Assumptions!$B$23 | G14: Runs on the staging node
A15: Domain registration | B15: Annual, amortised | C15: 600 | D15: EGP | E15: =C15/Assumptions!$B$23 | F15: =C15 | G15: One-off within the project window
A17: Sub-total | E17: =SUM(E5:E15) | F17: =SUM(F5:F15)
A18: TOTAL (rounded up) | E18: =CEILING(E17,10) | F18: =CEILING(F17,10) | G18: Feeds the Cost Breakdown sheet
A20: PDPL fallback | B20: If legal counsel rejects EU hosting, Egyptian local hosting is estimated at 3,000–8,000 EGP/month — an increase of roughly 4,000 to 28,500 EGP across the project window, which must come from contingency. This is an indicative range, not a quote: obtaining two firm local quotes is a Sprint 0 action item.

Sheet Cash Flow
A1: Cash Flow by Month
A2: Labour is spread by working weeks in each month. Infrastructure runs Aug–Dec.
A4: Month | B4: Weeks | C4: Backend | D4: Frontend | E4: DevOps | F4: Infrastructure | G4: Monthly total | H4: Cumulative
A5: Aug 2026 | B5: 3 | C5: =Assumptions!$B$15*Assumptions!$B$19/Assumptions!$B$10*B5 | D5: =Assumptions!$B$16*Assumptions!$B$20/Assumptions!$B$10*B5 | E5: =Assumptions!$B$17*Assumptions!$B$21/Assumptions!$B$10*B5 | F5: ='Infra and Tooling'!$F$18/Assumptions!$B$23 | G5: =SUM(C5:F5) | H5: =G5
A6: Sep 2026 | B6: 4.3 | C6: =Assumptions!$B$15*Assumptions!$B$19/Assumptions!$B$10*B6 | D6: =Assumptions!$B$16*Assumptions!$B$20/Assumptions!$B$10*B6 | E6: =Assumptions!$B$17*Assumptions!$B$21/Assumptions!$B$10*B6 | F6: ='Infra and Tooling'!$F$18/Assumptions!$B$23 | G6: =SUM(C6:F6) | H6: =H5+G6
A7: Oct 2026 | B7: 4.4 | C7: =Assumptions!$B$15*Assumptions!$B$19/Assumptions!$B$10*B7 | D7: =Assumptions!$B$16*Assumptions!$B$20/Assumptions!$B$10*B7 | E7: =Assumptions!$B$17*Assumptions!$B$21/Assumptions!$B$10*B7 | F7: ='Infra and Tooling'!$F$18/Assumptions!$B$23 | G7: =SUM(C7:F7) | H7: =H6+G7
A8: Nov 2026 | B8: 3.3 | C8: =Assumptions!$B$15*Assumptions!$B$19/Assumptions!$B$10*B8 | D8: =Assumptions!$B$16*Assumptions!$B$20/Assumptions!$B$10*B8 | E8: =Assumptions!$B$17*Assumptions!$B$21/Assumptions!$B$10*B8 | F8: ='Infra and Tooling'!$F$18/Assumptions!$B$23 | G8: =SUM(C8:F8) | H8: =H7+G8
A9: Dec 2026 | B9: 0 | C9: =Assumptions!$B$15*Assumptions!$B$19/Assumptions!$B$10*B9 | D9: =Assumptions!$B$16*Assumptions!$B$20/Assumptions!$B$10*B9 | E9: =Assumptions!$B$17*Assumptions!$B$21/Assumptions!$B$10*B9 | F9: ='Infra and Tooling'!$F$18/Assumptions!$B$23 | G9: =SUM(C9:F9) | H9: =H8+G9
A10: Total | B10: =SUM(B5:B9) | C10: =SUM(C5:C9) | D10: =SUM(D5:D9) | E10: =SUM(E5:E9) | F10: =SUM(F5:F9) | G10: =SUM(G5:G9) | H10: =H9
A12: Contingency (undrawn) | B12: ='Cost Breakdown'!$E$13 | D12: Weeks are working weeks within each calendar month across the 10 Aug – 20 Nov window. December carries infrastructure only, for hypercare.
A13: Committed + contingency | B13: =G10+B12
A14: Reconciles to budget | B14: =IF(ROUND(B13-Assumptions!$B$5,0)=0,"OK","CHECK — see note")

Sheet Scope Changes
A1: Scope Changes — Authentication & Super Admin Console
A2: Added after the first proposal draft. Phase 1 had no slack, so the cost is paid by displacement rather than absorbed silently.
A4: ADDED TO PHASE 1 — cannot wait for peak week
A5: Item | B5: BE days | C5: FE days | D5: Ops days | E5: Cost (EGP) | F5: Why it cannot wait
A6: Login, session policy, 2FA (Fortify) | B6: 1.5 | C6: 0 | D6: 0 | E6: =B6*Assumptions!$B$15/21+C6*Assumptions!$B$16/21+D6*Assumptions!$B$17/21 | F6: Gates everything else — nothing can be role-scoped until it exists
A7: User management + roles UI | B7: 1 | C7: 0.5 | D7: 0 | E7: =B7*Assumptions!$B$15/21+C7*Assumptions!$B$16/21+D7*Assumptions!$B$17/21 | F7: Onboarding and offboarding staff during peak week
A8: Permission matrix editor | B8: 0.5 | C8: 1 | D8: 0 | E8: =B8*Assumptions!$B$15/21+C8*Assumptions!$B$16/21+D8*Assumptions!$B$17/21 | F8: Tuning a role without a deployment
A9: Integrations console + credential rotation | B9: 2 | C9: 1 | D9: 0 | E9: =B9*Assumptions!$B$15/21+C9*Assumptions!$B$16/21+D9*Assumptions!$B$17/21 | F9: Rotating a leaked key, checking webhook health
A10: System health + dead-letter replay | B10: 2 | C10: 0.5 | D10: 0 | E10: =B10*Assumptions!$B$15/21+C10*Assumptions!$B$16/21+D10*Assumptions!$B$17/21 | F10: Replaying a failed webhook at 2am on Black Friday
A11: Added to Phase 1 | B11: =SUM(B6:B10) | C11: =SUM(C6:C10) | D11: =SUM(D6:D10) | E11: =SUM(E6:E10) | F11: Total engineering days added inside the Phase 1 window
A13: DISPLACED TO PHASE 1b — pays for the above
A14: Item | B14: BE days | C14: FE days | D14: Ops days | E14: Cost (EGP) | F14: Why it is safe to move
A15: Basic vendor scorecard (§10) | B15: 2 | C15: 2 | D15: 0 | E15: =B15*Assumptions!$B$15/21+C15*Assumptions!$B$16/21+D15*Assumptions!$B$17/21 | F15: A read model over data captured from day one — ships with full history
A16: Executive dashboard (§11) | B16: 1 | C16: 2 | D16: 0 | E16: =B16*Assumptions!$B$15/21+C16*Assumptions!$B$16/21+D16*Assumptions!$B$17/21 | F16: Same: a view over data already being collected, nothing lost retroactively
A17: Vendor product submission (§8.1) | B17: 2 | C17: 2 | D17: 0 | E17: =B17*Assumptions!$B$15/21+C17*Assumptions!$B$16/21+D17*Assumptions!$B$17/21 | F17: Vendors are onboarded through Ops today, so the manual path already exists
A18: Displaced out of Phase 1 | B18: =SUM(B15:B17) | C18: =SUM(C15:C17) | D18: =SUM(D15:D17) | E18: =SUM(E15:E17) | F18: Total engineering days moved to Phase 1b
A20: NET EFFECT ON PHASE 1 | B20: =B11-B18 | C20: =C11-C18 | D20: =D11-D18 | E20: =E11-E18
A22: Phase 1 budget impact | B22: =IF(E20<=0,"NONE — the trade pays for itself","SHORTFALL — see Sensitivity")
A24: Stated plainly: the console is real work and Phase 1 had no slack, so something had to give. Displacing three read-only surfaces is the cheapest way to pay for it — they are views over data the system collects from day one, so they lose no history and simply arrive three weeks after go-live. The alternative, drawing on contingency, is modelled on the Sensitivity sheet and is not recommended while the PDPL hosting risk is open.

Sheet Phase 1b and 2
A1: Phase 1b and Phase 2 — Indicative Estimates
A2: Not funded by the 300,000 EGP Phase 1 budget. Presented so the client can plan.
A4: PHASE 1b — 23 Nov to 11 Dec 2026 (3 weeks)
A5: Deliverable | B5: BE days | C5: FE days | D5: Ops days | E5: Cost (EGP) | F5: Notes
A6: Customer self-service returns portal | B6: 4 | C6: 8 | D6: 1 | E6: =B6*Assumptions!$B$15/21+C6*Assumptions!$B$16/21+D6*Assumptions!$B$17/21 | F6: Order number + phone lookup, no account required
A7: Returns analytics dashboard | B7: 4 | C7: 3 | D7: 0 | E7: =B7*Assumptions!$B$15/21+C7*Assumptions!$B$16/21+D7*Assumptions!$B$17/21 | F7: By reason, vendor and stakeholder
A8: E-stebdal parallel-run validation | B8: 2 | C8: 1 | D8: 1 | E8: =B8*Assumptions!$B$15/21+C8*Assumptions!$B$16/21+D8*Assumptions!$B$17/21 | F8: Data parity check before January cutover
A9: Super Admin: business rules engine UI | B9: 3 | C9: 2 | D9: 0 | E9: =B9*Assumptions!$B$15/21+C9*Assumptions!$B$16/21+D9*Assumptions!$B$17/21 | F9: Phase 1 seeds these rules by migration
A10: Super Admin: report builder + scheduling | B10: 2 | C10: 2 | D10: 0 | E10: =B10*Assumptions!$B$15/21+C10*Assumptions!$B$16/21+D10*Assumptions!$B$17/21 | F10: Phase 1 ships a fixed set of built-in reports
A11: Basic vendor scorecard (displaced from P1) | B11: 2 | C11: 2 | D11: 0 | E11: =B11*Assumptions!$B$15/21+C11*Assumptions!$B$16/21+D11*Assumptions!$B$17/21 | F11: Read model - ships with full history
A12: Executive dashboard (displaced from P1) | B12: 1 | C12: 2 | D12: 0 | E12: =B12*Assumptions!$B$15/21+C12*Assumptions!$B$16/21+D12*Assumptions!$B$17/21 | F12: Read model - ships with full history
A13: Vendor product submission (displaced from P1) | B13: 2 | C13: 2 | D13: 0 | E13: =B13*Assumptions!$B$15/21+C13*Assumptions!$B$16/21+D13*Assumptions!$B$17/21 | F13: Vendors onboard through Ops in the interim
A14: Phase 1b total | B14: =SUM(B6:B13) | C14: =SUM(C6:C13) | D14: =SUM(D6:D13) | E14: =SUM(E6:E13) | F14: Assumes 21 working days per month
A16: PHASE 2 — from January 2027
A17: Deliverable | B17: BE days | C17: FE days | D17: Ops days | E17: Cost (EGP) | F17: Requirement
A18: Raw fabric inventory, BOM and forecasting | B18: 15 | C18: 6 | D18: 0 | E18: =B18*Assumptions!$B$15/21+C18*Assumptions!$B$16/21+D18*Assumptions!$B$17/21 | F18: Req 7.2 — largest single Phase 2 item
A19: Automated Paymob Send disbursement | B19: 8 | C19: 2 | D19: 1 | E19: =B19*Assumptions!$B$15/21+C19*Assumptions!$B$16/21+D19*Assumptions!$B$17/21 | F19: Req 8.6 — human approval gate retained
A20: Second courier adapter | B20: 10 | C20: 3 | D20: 1 | E20: =B20*Assumptions!$B$15/21+C20*Assumptions!$B$16/21+D20*Assumptions!$B$17/21 | F20: Req 3.1 — per-item courier selection
A21: Advanced vendor scorecard and penalties | B21: 10 | C21: 6 | D21: 0 | E21: =B21*Assumptions!$B$15/21+C21*Assumptions!$B$16/21+D21*Assumptions!$B$17/21 | F21: Req 10
A22: Executive BI dashboard | B22: 8 | C22: 6 | D22: 0 | E22: =B22*Assumptions!$B$15/21+C22*Assumptions!$B$16/21+D22*Assumptions!$B$17/21 | F22: Req 11
A23: Automated recall / win-back workflows | B23: 7 | C23: 4 | D23: 0 | E23: =B23*Assumptions!$B$15/21+C23*Assumptions!$B$16/21+D23*Assumptions!$B$17/21 | F23: The §1.2 revenue case, automated
A24: Phase 2 total | B24: =SUM(B18:B23) | C24: =SUM(C18:C23) | D24: =SUM(D18:D23) | E24: =SUM(E18:E23) | F24: Excludes infrastructure
A26: Phase 1 + 1b + 2 combined | E26: ='Cost Breakdown'!$E$15+E14+E24

Sheet Sensitivity
A1: Sensitivity Analysis
A2: What the budget buys under different assumptions — and the three levers if the schedule slips.
A4: BUDGET SENSITIVITY
A5: Scenario | B5: Budget (EGP) | C5: Person-months | D5: Δ vs plan | E5: Scope consequence
A6: Budget −20% | B6: =Assumptions!$B$5*0.8 | C6: =(B6-'Infra and Tooling'!$F$18-B6*'Cost Breakdown'!$F$13)/'Cost Breakdown'!$B$19 | D6: =C6-Assumptions!$B$26 | E6: Phase 1 loses settlement automation AND the vendor scorecard. Order, shipping, returns and finance survive.
A7: Budget −10% | B7: =Assumptions!$B$5*0.9 | C7: =(B7-'Infra and Tooling'!$F$18-B7*'Cost Breakdown'!$F$13)/'Cost Breakdown'!$B$19 | D7: =C7-Assumptions!$B$26 | E7: Vendor scorecard deferred to Phase 1b. Everything else holds.
A8: Plan as proposed | B8: =Assumptions!$B$5*1.0 | C8: =(B8-'Infra and Tooling'!$F$18-B8*'Cost Breakdown'!$F$13)/'Cost Breakdown'!$B$19 | D8: =C8-Assumptions!$B$26 | E8: Full Phase 1 scope as defined in proposal §3.1. Zero slack.
A9: Budget +10% | B9: =Assumptions!$B$5*1.1 | C9: =(B9-'Infra and Tooling'!$F$18-B9*'Cost Breakdown'!$F$13)/'Cost Breakdown'!$B$19 | D9: =C9-Assumptions!$B$26 | E9: Restores ~3 weeks of slack — the single most valuable addition, given Phase 1 currently has none.
A10: Budget +20% | B10: =Assumptions!$B$5*1.2 | C10: =(B10-'Infra and Tooling'!$F$18-B10*'Cost Breakdown'!$F$13)/'Cost Breakdown'!$B$19 | D10: =C10-Assumptions!$B$26 | E10: Pulls the customer self-service returns portal back into Phase 1.
A12: TEAM MODEL SENSITIVITY
A13: Engagement model | B13: Rate multiple | C13: Person-months | D13: Δ vs plan | E13: Verdict
A14: In-house salaried (assumed) | B14: 1 | C14: =Assumptions!$B$26/B14 | D14: =C14-Assumptions!$B$26 | E14: Phase 1 scope is achievable. This is the model the budget is built on.
A15: Freelance / contractor | B15: 1.5 | C15: =Assumptions!$B$26/B15 | D15: =C15-Assumptions!$B$26 | E15: Buys roughly two thirds of the person-months. Phase 1 must shed settlement, scorecard and vendor portal v1.
A16: Agency / software house | B16: 2.5 | C16: =Assumptions!$B$26/B16 | D16: =C16-Assumptions!$B$26 | E16: Buys under half. 300,000 EGP funds an MVP — Shopify sync, item splitting and shipping only. Returns and finance would not fit.
A19: FUNDING THE ADMIN CONSOLE
A20: Option | B20: Cost (EGP) | C20: Contingency left | D20: Preference | E20: Consequence
A21: 1. Displace 11 days of read-only UI | B21: 0 | C21: ='Cost Breakdown'!$E$13 | D21: recommended | E21: Vendor scorecard, executive dashboard and vendor product submission move to Phase 1b. All three are views over data captured from day one, so nothing is lost retroactively.
A22: 2. Draw on contingency | B22: ='Scope Changes'!$E$11 | C22: ='Cost Breakdown'!$E$13-B22 | D22: not while PDPL is open | E22: Arithmetically it fits, but leaves too little against risk R1 - the PDPL hosting fallback alone could need up to 28,500 EGP.
A23: 3. Increase the budget | B23: ='Scope Changes'!$E$11 | C23: ='Cost Breakdown'!$E$13-B23 | D23: client's call | E23: Roughly 16,000-20,000 EGP. Keeps every Phase 1 surface and restores the contingency.
A26: SCHEDULE LEVERS
A27: Lever | B27: Cost (EGP) | C27: Time recovered | D27: Preference | E27: Trade-off
A28: 1. Cut scope | B28: 0 | C28: ~2 weeks | D28: Preferred | E28: Defer settlement automation and vendor scorecard to Phase 1b. No cash cost.
A29: 2. Extend timeline | B29: 0 | C29: Unlimited | D29: Second | E29: Go live in December, after Black Friday. Removes all peak-week risk but forfeits a full peak season of benefit.
A30: 3. Add a 2nd backend engineer | B30: =Assumptions!$B$15*3*1 | C30: ~3 weeks | D30: Least effective | E30: Only works if committed by mid-September. Later than that, onboarding drag exceeds the capacity added.

Sheet ROI
A1: Return on Investment
A2: The case rests on recovered failed deliveries, not on data-entry savings. Proposal §1.2.
A4: OPERATIONAL BASELINE — from the client's own data
A5: Measure | B5: Value | C5: Unit | D5: Source
A6: Item rows analysed | B6: 18341 | C6: items | D6: Copy of Orders, 1 Jan – 8 Aug 2026
A7: Failed delivery (FD Allow Open Shipment) | B7: 3743 | C7: items | D7: Final status column
A8: Returned to origin (RTO) | B8: 2359 | C8: items | D8: Final status column
A9: Total failed items | B9: =B7+B8 | C9: items | D9: FD + RTO
A10: Average item value | B10: 897 | C10: EGP | D10: GMV ÷ item rows
A11: GMV that shipped and came back | B11: =B9*B10 | C11: EGP | D11: Failed items × average value
A13: Failed items actually worked (Send messages) | B13: 1430 | C13: items | D13: Recall Status column
A14: Recovered into new orders | B14: 273 | C14: items | D14: Recall Status = Create new orders
A15: Current recovery rate | B15: =B14/B13 | C15: % | D15: Recovered ÷ worked
A16: Failed items never worked | B16: =B9-B13 | C16: items | D16: Total failed − worked
A18: RECOVERY SCENARIOS — annualised
A19: Scenario | B19: Recovered items / yr | C19: Recovered GMV / yr (EGP) | D19: Assumption
A20: Conservative | B20: =B16*(B15/2)*12/7 | C20: =B20*B10 | D20: Half the current recovery rate applied to items never worked. Deliberately pessimistic: worked items were probably the most promising.
A21: At parity | B21: =(B9*B15-B14)*12/7 | C21: =B21*B10 | D21: Current 19.1% recovery rate applied across all failed items, net of what is already recovered today.
A23: PAYBACK
A24: Phase 1 build cost | B24: ='Cost Breakdown'!$E$15 | D24: These are GMV figures, not profit. The platform realises commission and margin on recovered orders, not the full value. The point is the order of magnitude: even the conservative case returns more than twice the build cost in GMV within year one, and the recall queue is a permanent capability.
A25: Recovered GMV, conservative case | B25: =C20
A26: Ratio — recovered GMV to build cost | B26: =B25/B24
A28: RECURRING OFFSETS
A29: E-stebdal subscription — monthly | B29: 0 | D29: CLIENT TO CONFIRM. Enter the current monthly subscription; the annual saving below will calculate. Retired at January 2027 cutover.
A30: Annual saving from retiring E-stebdal | B30: =B29*12
A31: Manual data entry displaced | B31: =B6/155 | C31: rows / working day | D31: Across 32 columns with cross-system lookups per row. A real but soft saving — not counted in the payback figure above.
